GcpShangDeRengongzhinengShiyongZhinanChuyi/README.md
GcpShangDeRengongzhinengShiyongZhinanChuyi/__init__.py
GcpShangDeRengongzhinengShiyongZhinanChuyi/__main__.py
GcpShangDeRengongzhinengShiyongZhinanChuyi/file.epub
GcpShangDeRengongzhinengShiyongZhinanChuyi/index.html
GcpShangDeRengongzhinengShiyongZhinanChuyi/css/__init__.py
GcpShangDeRengongzhinengShiyongZhinanChuyi/css/annotations.css
GcpShangDeRengongzhinengShiyongZhinanChuyi/css/main.css
GcpShangDeRengongzhinengShiyongZhinanChuyi/css/normalize.css
GcpShangDeRengongzhinengShiyongZhinanChuyi/css/popup.css
GcpShangDeRengongzhinengShiyongZhinanChuyi/font/__init__.py
GcpShangDeRengongzhinengShiyongZhinanChuyi/font/fontello.eot
GcpShangDeRengongzhinengShiyongZhinanChuyi/font/fontello.svg
GcpShangDeRengongzhinengShiyongZhinanChuyi/font/fontello.ttf
GcpShangDeRengongzhinengShiyongZhinanChuyi/font/fontello.woff
GcpShangDeRengongzhinengShiyongZhinanChuyi/img/__init__.py
GcpShangDeRengongzhinengShiyongZhinanChuyi/img/annotator-glyph-sprite.png
GcpShangDeRengongzhinengShiyongZhinanChuyi/img/annotator-icon-sprite.png
GcpShangDeRengongzhinengShiyongZhinanChuyi/img/apple-touch-icon.png
GcpShangDeRengongzhinengShiyongZhinanChuyi/img/cancelfullscreen.png
GcpShangDeRengongzhinengShiyongZhinanChuyi/img/close.png
GcpShangDeRengongzhinengShiyongZhinanChuyi/img/fullscreen.png
GcpShangDeRengongzhinengShiyongZhinanChuyi/img/loader.gif
GcpShangDeRengongzhinengShiyongZhinanChuyi/img/menu-icon.png
GcpShangDeRengongzhinengShiyongZhinanChuyi/img/save.png
GcpShangDeRengongzhinengShiyongZhinanChuyi/img/saved.png
GcpShangDeRengongzhinengShiyongZhinanChuyi/img/settings-s.png
GcpShangDeRengongzhinengShiyongZhinanChuyi/img/settings.png
GcpShangDeRengongzhinengShiyongZhinanChuyi/img/star.png
GcpShangDeRengongzhinengShiyongZhinanChuyi/js/__init__.py
GcpShangDeRengongzhinengShiyongZhinanChuyi/js/epub.js
GcpShangDeRengongzhinengShiyongZhinanChuyi/js/epub.min.js
GcpShangDeRengongzhinengShiyongZhinanChuyi/js/epub.min.map
gcp_shang_de_rengongzhineng_shiyong_zhinan_chuyi-2024.3.6.0.dist-info/METADATA
gcp_shang_de_rengongzhineng_shiyong_zhinan_chuyi-2024.3.6.0.dist-info/WHEEL
gcp_shang_de_rengongzhineng_shiyong_zhinan_chuyi-2024.3.6.0.dist-info/entry_points.txt
gcp_shang_de_rengongzhineng_shiyong_zhinan_chuyi-2024.3.6.0.dist-info/top_level.txt
gcp_shang_de_rengongzhineng_shiyong_zhinan_chuyi-2024.3.6.0.dist-info/RECORD
